browser_history_analytics_2/__init__.py
browser_history_analytics_2/app.py
browser_history_analytics_2/graphs.py
browser_history_analytics_2/main.py
browser_history_analytics_2/utils.py
browser_history_analytics_2-1.0.1.dist-info/licenses/LICENSE
browser_history_analytics_2-1.0.1.dist-info/METADATA
browser_history_analytics_2-1.0.1.dist-info/WHEEL
browser_history_analytics_2-1.0.1.dist-info/entry_points.txt
browser_history_analytics_2-1.0.1.dist-info/top_level.txt
browser_history_analytics_2-1.0.1.dist-info/RECORD
