Metadata-Version: 2.4
Name: browser-history-analytics-2
Version: 1.0.1
Summary: A package to visualize your browser history :D
Author: Arpit Sengar (arpy8)
Classifier: Programming Language :: Python :: 3
Classifier: License :: OSI Approved :: MIT License
Classifier: Operating System :: OS Independent
Requires-Python: >=3.10
License-File: LICENSE
Requires-Dist: rich
Requires-Dist: pandas
Requires-Dist: streamlit
Requires-Dist: plotly[express]
Requires-Dist: browser-history
Requires-Dist: setuptools==66.1.1
Dynamic: author
Dynamic: classifier
Dynamic: description
Dynamic: description-content-type
Dynamic: license-file
Dynamic: requires-dist
Dynamic: requires-python
Dynamic: summary
